[
  {
    "word": "glance",
    "options": [
      "袭击",
      "处理",
      "特权",
      "一眼"
    ],
    "answer": 3,
    "audio": "https://john-wm-qiu.github.io/IELTS_Listening/words/pronunciation/g/glance.wav"
  },
  {
    "word": "copper",
    "options": [
      "铜",
      "总理",
      "有毒的",
      "强化"
    ],
    "answer": 0,
    "audio": "https://john-wm-qiu.github.io/IELTS_Listening/words/pronunciation/c/copper.wav"
  },
  {
    "word": "cult",
    "options": [
      "存在",
      "王冠",
      "中间的",
      "邪教"
    ],
    "answer": 3,
    "audio": "https://john-wm-qiu.github.io/IELTS_Listening/words/pronunciation/c/cult.wav"
  },
  {
    "word": "continually",
    "options": [
      "容忍",
      "不断",
      "相关性",
      "碰撞"
    ],
    "answer": 1,
    "audio": "https://john-wm-qiu.github.io/IELTS_Listening/words/pronunciation/c/continually.wav"
  },
  {
    "word": "inability",
    "options": [
      "泄露",
      "无力",
      "大陆",
      "公平"
    ],
    "answer": 1,
    "audio": "https://john-wm-qiu.github.io/IELTS_Listening/words/pronunciation/i/inability.wav"
  },
  {
    "word": "patent",
    "options": [
      "专利",
      "意识",
      "叹",
      "大陆"
    ],
    "answer": 0,
    "audio": "https://john-wm-qiu.github.io/IELTS_Listening/words/pronunciation/p/patent.wav"
  },
  {
    "word": "superb",
    "options": [
      "有利可图",
      "定罪",
      "与此同时",
      "高超"
    ],
    "answer": 3,
    "audio": "https://john-wm-qiu.github.io/IELTS_Listening/words/pronunciation/s/superb.wav"
  },
  {
    "word": "collective",
    "options": [
      "插入",
      "反抗",
      "转型",
      "集体"
    ],
    "answer": 3,
    "audio": "https://john-wm-qiu.github.io/IELTS_Listening/words/pronunciation/c/collective.wav"
  },
  {
    "word": "reform",
    "options": [
      "改革",
      "专栏作家",
      "进气",
      "成熟"
    ],
    "answer": 0,
    "audio": "https://john-wm-qiu.github.io/IELTS_Listening/words/pronunciation/r/reform.wav"
  },
  {
    "word": "snap",
    "options": [
      "有效性",
      "硬件",
      "折断",
      "丢弃"
    ],
    "answer": 2,
    "audio": "https://john-wm-qiu.github.io/IELTS_Listening/words/pronunciation/s/snap.wav"
  },
  {
    "word": "prosecute",
    "options": [
      "名册",
      "完全",
      "监禁",
      "起诉"
    ],
    "answer": 3,
    "audio": "https://john-wm-qiu.github.io/IELTS_Listening/words/pronunciation/p/prosecute.wav"
  },
  {
    "word": "integrated",
    "options": [
      "面对",
      "融合的",
      "干涉",
      "邻接"
    ],
    "answer": 1,
    "audio": "https://john-wm-qiu.github.io/IELTS_Listening/words/pronunciation/i/integrated.wav"
  },
  {
    "word": "unveil",
    "options": [
      "教育家",
      "进化",
      "揭开",
      "神"
    ],
    "answer": 2,
    "audio": "https://john-wm-qiu.github.io/IELTS_Listening/words/pronunciation/u/unveil.wav"
  },
  {
    "word": "fleet",
    "options": [
      "破坏",
      "努力",
      "荣耀",
      "舰队"
    ],
    "answer": 3,
    "audio": "https://john-wm-qiu.github.io/IELTS_Listening/words/pronunciation/f/fleet.wav"
  },
  {
    "word": "prestigious",
    "options": [
      "努力",
      "享有声望",
      "宽带",
      "肾"
    ],
    "answer": 1,
    "audio": "https://john-wm-qiu.github.io/IELTS_Listening/words/pronunciation/p/prestigious.wav"
  },
  {
    "word": "hostile",
    "options": [
      "敌对",
      "范围",
      "管道",
      "较少"
    ],
    "answer": 0,
    "audio": "https://john-wm-qiu.github.io/IELTS_Listening/words/pronunciation/h/hostile.wav"
  },
  {
    "word": "refuge",
    "options": [
      "周到",
      "条款",
      "避难所",
      "酷刑"
    ],
    "answer": 2,
    "audio": "https://john-wm-qiu.github.io/IELTS_Listening/words/pronunciation/r/refuge.wav"
  },
  {
    "word": "legislation",
    "options": [
      "削减",
      "肠",
      "宣传",
      "立法"
    ],
    "answer": 3,
    "audio": "https://john-wm-qiu.github.io/IELTS_Listening/words/pronunciation/l/legislation.wav"
  },
  {
    "word": "sensitivity",
    "options": [
      "战士",
      "合理的",
      "灵敏度",
      "高超"
    ],
    "answer": 2,
    "audio": "https://john-wm-qiu.github.io/IELTS_Listening/words/pronunciation/s/sensitivity.wav"
  },
  {
    "word": "maximize",
    "options": [
      "交易",
      "礼貌",
      "最大化",
      "腐败"
    ],
    "answer": 2,
    "audio": "https://john-wm-qiu.github.io/IELTS_Listening/words/pronunciation/m/maximize.wav"
  },
  {
    "word": "sin",
    "options": [
      "位于",
      "伤亡",
      "大二",
      "罪"
    ],
    "answer": 3,
    "audio": "https://john-wm-qiu.github.io/IELTS_Listening/words/pronunciation/s/sin.wav"
  },
  {
    "word": "melody",
    "options": [
      "质地",
      "思考",
      "旋律",
      "战斗"
    ],
    "answer": 2,
    "audio": "https://john-wm-qiu.github.io/IELTS_Listening/words/pronunciation/m/melody.wav"
  },
  {
    "word": "partial",
    "options": [
      "司法",
      "复兴",
      "部分的",
      "国籍"
    ],
    "answer": 2,
    "audio": "https://john-wm-qiu.github.io/IELTS_Listening/words/pronunciation/p/partial.wav"
  },
  {
    "word": "suspension",
    "options": [
      "诗",
      "判决",
      "暂停",
      "贮存"
    ],
    "answer": 2,
    "audio": "https://john-wm-qiu.github.io/IELTS_Listening/words/pronunciation/s/suspension.wav"
  },
  {
    "word": "indulge",
    "options": [
      "周到",
      "战略",
      "辞职",
      "放纵"
    ],
    "answer": 3,
    "audio": "https://john-wm-qiu.github.io/IELTS_Listening/words/pronunciation/i/indulge.wav"
  },
  {
    "word": "selective",
    "options": [
      "选择性",
      "明确",
      "与此同时",
      "苗圃"
    ],
    "answer": 0,
    "audio": "https://john-wm-qiu.github.io/IELTS_Listening/words/pronunciation/s/selective.wav"
  },
  {
    "word": "spin",
    "options": [
      "保证",
      "大陆",
      "目光",
      "旋转"
    ],
    "answer": 3,
    "audio": "https://john-wm-qiu.github.io/IELTS_Listening/words/pronunciation/s/spin.wav"
  },
  {
    "word": "hostage",
    "options": [
      "愤怒",
      "前景",
      "人质",
      "战士"
    ],
    "answer": 2,
    "audio": "https://john-wm-qiu.github.io/IELTS_Listening/words/pronunciation/h/hostage.wav"
  },
  {
    "word": "tender",
    "options": [
      "公平",
      "投标",
      "郊游",
      "进化"
    ],
    "answer": 1,
    "audio": "https://john-wm-qiu.github.io/IELTS_Listening/words/pronunciation/t/tender.wav"
  },
  {
    "word": "withdrawal",
    "options": [
      "行进",
      "传",
      "转换",
      "提取"
    ],
    "answer": 3,
    "audio": "https://john-wm-qiu.github.io/IELTS_Listening/words/pronunciation/w/withdrawal.wav"
  },
  {
    "word": "breakdown",
    "options": [
      "游说",
      "搅拌",
      "分解",
      "减少"
    ],
    "answer": 2,
    "audio": "https://john-wm-qiu.github.io/IELTS_Listening/words/pronunciation/b/breakdown.wav"
  },
  {
    "word": "syndrome",
    "options": [
      "女同性恋",
      "强奸",
      "综合征",
      "桶"
    ],
    "answer": 2,
    "audio": "https://john-wm-qiu.github.io/IELTS_Listening/words/pronunciation/s/syndrome.wav"
  },
  {
    "word": "cargo",
    "options": [
      "繁荣",
      "副",
      "连续的",
      "货物"
    ],
    "answer": 3,
    "audio": "https://john-wm-qiu.github.io/IELTS_Listening/words/pronunciation/c/cargo.wav"
  },
  {
    "word": "instinct",
    "options": [
      "本能",
      "挫折",
      "设置",
      "海军"
    ],
    "answer": 0,
    "audio": "https://john-wm-qiu.github.io/IELTS_Listening/words/pronunciation/i/instinct.wav"
  },
  {
    "word": "disturbing",
    "options": [
      "令人不安的",
      "启示",
      "修辞",
      "一眼"
    ],
    "answer": 0,
    "audio": "https://john-wm-qiu.github.io/IELTS_Listening/words/pronunciation/d/disturbing.wav"
  },
  {
    "word": "smash",
    "options": [
      "心爱",
      "合作",
      "压碎",
      "粉碎"
    ],
    "answer": 3,
    "audio": "https://john-wm-qiu.github.io/IELTS_Listening/words/pronunciation/s/smash.wav"
  },
  {
    "word": "gathering",
    "options": [
      "脆弱性",
      "采集",
      "融合的",
      "注射"
    ],
    "answer": 1,
    "audio": "https://john-wm-qiu.github.io/IELTS_Listening/words/pronunciation/g/gathering.wav"
  },
  {
    "word": "embarrassment",
    "options": [
      "坑",
      "尴尬",
      "辉煌",
      "订户"
    ],
    "answer": 1,
    "audio": "https://john-wm-qiu.github.io/IELTS_Listening/words/pronunciation/e/embarrassment.wav"
  },
  {
    "word": "threshold",
    "options": [
      "赌注",
      "合作",
      "临界点",
      "仇恨"
    ],
    "answer": 2,
    "audio": "https://john-wm-qiu.github.io/IELTS_Listening/words/pronunciation/t/threshold.wav"
  },
  {
    "word": "pad",
    "options": [
      "讲道",
      "软垫",
      "起源",
      "圣"
    ],
    "answer": 1,
    "audio": "https://john-wm-qiu.github.io/IELTS_Listening/words/pronunciation/p/pad.wav"
  }
]